llama_index_supervisor/__init__.py
llama_index_supervisor/agent_name.py
llama_index_supervisor/events.py
llama_index_supervisor/handoff.py
llama_index_supervisor/supervisor.py
llama_index_supervisor-0.1.11.dist-info/METADATA
llama_index_supervisor-0.1.11.dist-info/WHEEL
llama_index_supervisor-0.1.11.dist-info/top_level.txt
llama_index_supervisor-0.1.11.dist-info/RECORD
