Metadata-Version: 2.4
Name: llama_index_supervisor
Version: 0.1.11
Summary: This project is a Python-based multi-agent supervisor inspired by LangGraph, adapted for llama_index. It delegates tasks to specialized agents and tools, processes function-calling LLM responses, and manages conversation history. The structured workflow handles tool calls, processes agent handoffs with error handling, and provides flexible message management for hierarchical multi-agent systems.
Requires-Python: >=3.10
Requires-Dist: llama-index-core>=0.12.27
